disca/__init__.py
disca/cli.py
disca/client.py
disca/state.py
disca/voice.py
disca/api/__init__.py
disca/api/client.py
disca/api/http.py
disca/api/ratelimit.py
disca/bot/__init__.py
disca/bot/bot.py
disca/bot/command.py
disca/bot/parser.py
disca/bot/plugin.py
disca/bot/storage.py
disca/gateway/__init__.py
disca/gateway/client.py
disca/gateway/events.py
disca/gateway/ipc.py
disca/gateway/packets.py
disca/gateway/sharder.py
disca/gateway/encoding/__init__.py
disca/gateway/encoding/base.py
disca/gateway/encoding/etf.py
disca/gateway/encoding/json.py
disca/types/__init__.py
disca/types/base.py
disca/types/channel.py
disca/types/guild.py
disca/types/invite.py
disca/types/message.py
disca/types/oauth.py
disca/types/permissions.py
disca/types/user.py
disca/types/voice.py
disca/types/webhook.py
disca/util/__init__.py
disca/util/backdoor.py
disca/util/chains.py
disca/util/config.py
disca/util/emitter.py
disca/util/enum.py
disca/util/functional.py
disca/util/hashmap.py
disca/util/limiter.py
disca/util/logging.py
disca/util/paginator.py
disca/util/sanitize.py
disca/util/serializer.py
disca/util/snowflake.py
disca/util/string.py
disca/util/threadlocal.py
disca/util/websocket.py
disca-0.0.14.dist-info/METADATA
disca-0.0.14.dist-info/WHEEL
disca-0.0.14.dist-info/top_level.txt
disca-0.0.14.dist-info/RECORD
