Metadata-Version: 2.1
Name: disca
Version: 0.0.14
Summary: A Python library for Discord
Home-page: https://github.com/py57/disca
Author: py57
License: MIT
Platform: UNKNOWN
Classifier: Development Status :: 4 - Beta
Classifier: License :: OSI Approved :: MIT License
Classifier: Intended Audience :: Developers
Classifier: Natural Language :: English
Classifier: Operating System :: OS Independent
Classifier: Programming Language :: Python :: 3.6
Classifier: Programming Language :: Python :: 3.7
Classifier: Programming Language :: Python :: 3.8
Classifier: Programming Language :: Python :: 3.9
Classifier: Topic :: Internet
Classifier: Topic :: Software Development :: Libraries
Classifier: Topic :: Software Development :: Libraries :: Python Modules
Classifier: Topic :: Utilities
Requires-Dist: gevent (==21.8.0)
Requires-Dist: requests (==2.26.0)
Requires-Dist: six (==1.16.0)
Requires-Dist: websocket-client (==1.2.1)
Provides-Extra: docs
Requires-Dist: biblio (==0.0.4) ; extra == 'docs'
Provides-Extra: http
Requires-Dist: flask (==2.0.2) ; extra == 'http'
Provides-Extra: music
Requires-Dist: youtube-dl (==2021.6.6) ; extra == 'music'
Provides-Extra: performance
Requires-Dist: earl-etf (==2.1.2) ; extra == 'performance'
Requires-Dist: ujson (==4.2.0) ; extra == 'performance'
Requires-Dist: wsaccel (==0.6.3) ; extra == 'performance'
Provides-Extra: sharding
Requires-Dist: gipc (==1.3.0) ; extra == 'sharding'
Provides-Extra: voice
Requires-Dist: telecom-py (==0.0.4) ; extra == 'voice'
Provides-Extra: yaml
Requires-Dist: pyyaml (==6.0) ; extra == 'yaml'
